{
    "name": "root",
    "gauges": {
        "HitPuck.Policy.Entropy.mean": {
            "value": 1.19297194480896,
            "min": 1.19297194480896,
            "max": 1.3211851119995117,
            "count": 10
        },
        "HitPuck.Policy.Entropy.sum": {
            "value": 59648.59765625,
            "min": 59648.59765625,
            "max": 66059.2578125,
            "count": 10
        },
        "HitPuck.Step.mean": {
            "value": 499968.0,
            "min": 49992.0,
            "max": 499968.0,
            "count": 10
        },
        "HitPuck.Step.sum": {
            "value": 499968.0,
            "min": 49992.0,
            "max": 499968.0,
            "count": 10
        },
        "HitPuck.Policy.ExtrinsicValueEstimate.mean": {
            "value": 218.6453094482422,
            "min": -210.0122528076172,
            "max": 218.6453094482422,
            "count": 10
        },
        "HitPuck.Policy.ExtrinsicValueEstimate.sum": {
            "value": 218645.3125,
            "min": -210012.25,
            "max": 218645.3125,
            "count": 10
        },
        "HitPuck.Environment.EpisodeLength.mean": {
            "value": 199.0,
            "min": 199.0,
            "max": 199.0,
            "count": 10
        },
        "HitPuck.Environment.EpisodeLength.sum": {
            "value": 49750.0,
            "min": 49352.0,
            "max": 49750.0,
            "count": 10
        },
        "HitPuck.Environment.CumulativeReward.mean": {
            "value": 484.28276406330616,
            "min": -4225.015156057548,
            "max": 534.5601525732594,
            "count": 10
        },
        "HitPuck.Environment.CumulativeReward.sum": {
            "value": 121070.69101582654,
            "min": -1052028.7738583293,
            "max": 132570.91783816833,
            "count": 10
        },
        "HitPuck.Policy.ExtrinsicReward.mean": {
            "value": 484.28276406330616,
            "min": -4225.015156057548,
            "max": 534.5601525732594,
            "count": 10
        },
        "HitPuck.Policy.ExtrinsicReward.sum": {
            "value": 121070.69101582654,
            "min": -1052028.7738583293,
            "max": 132570.91783816833,
            "count": 10
        },
        "HitPuck.Losses.PolicyLoss.mean": {
            "value": 0.022679084005455173,
            "min": 0.021295592004122836,
            "max": 0.028202120757972203,
            "count": 10
        },
        "HitPuck.Losses.PolicyLoss.sum": {
            "value": 0.11339542002727587,
            "min": 0.0865430632683759,
            "max": 0.1264439476498713,
            "count": 10
        },
        "HitPuck.Losses.ValueLoss.mean": {
            "value": 8187.905898437501,
            "min": 3570.1141324869795,
            "max": 218198.81447753907,
            "count": 10
        },
        "HitPuck.Losses.ValueLoss.sum": {
            "value": 40939.5294921875,
            "min": 17850.570662434897,
            "max": 872795.2579101563,
            "count": 10
        },
        "HitPuck.Policy.LearningRate.mean": {
            "value": 1.6659934446720005e-05,
            "min": 1.6659934446720005e-05,
            "max": 0.0002846064051312,
            "count": 10
        },
        "HitPuck.Policy.LearningRate.sum": {
            "value": 8.329967223360003e-05,
            "min": 8.329967223360003e-05,
            "max": 0.001284432071856,
            "count": 10
        },
        "HitPuck.Policy.Epsilon.mean": {
            "value": 0.10555328,
            "min": 0.10555328,
            "max": 0.19486880000000004,
            "count": 10
        },
        "HitPuck.Policy.Epsilon.sum": {
            "value": 0.5277664,
            "min": 0.5002336000000002,
            "max": 0.9281440000000001,
            "count": 10
        },
        "HitPuck.Policy.Beta.mean": {
            "value": 0.00028710867200000014,
            "min": 0.00028710867200000014,
            "max": 0.004743953119999999,
            "count": 10
        },
        "HitPuck.Policy.Beta.sum": {
            "value": 0.0014355433600000008,
            "min": 0.0014355433600000008,
            "max": 0.0214143856,
            "count": 10
        },
        "HitPuck.IsTraining.mean": {
            "value": 1.0,
            "min": 1.0,
            "max": 1.0,
            "count": 10
        },
        "HitPuck.IsTraining.sum": {
            "value": 1.0,
            "min": 1.0,
            "max": 1.0,
            "count": 10
        }
    },
    "metadata": {
        "timer_format_version": "0.1.0",
        "start_time_seconds": "1651949176",
        "python_version": "3.9.1 (tags/v3.9.1:1e5d33e, Dec  7 2020, 17:08:21) [MSC v.1927 64 bit (AMD64)]",
        "command_line_arguments": "D:\\Projects\\Unity\\SkynetProject\\venv\\Scripts\\mlagents-learn config.yaml --run-id=RemoteTest",
        "mlagents_version": "0.29.0",
        "mlagents_envs_version": "0.29.0",
        "communication_protocol_version": "1.5.0",
        "pytorch_version": "1.11.0+cpu",
        "numpy_version": "1.21.2",
        "end_time_seconds": "1651950500"
    },
    "total": 1324.2920436000002,
    "count": 1,
    "self": 0.004559700000299927,
    "children": {
        "run_training.setup": {
            "total": 0.11105830000000028,
            "count": 1,
            "self": 0.11105830000000028
        },
        "TrainerController.start_learning": {
            "total": 1324.1764256,
            "count": 1,
            "self": 2.6651305999660053,
            "children": {
                "TrainerController._reset_env": {
                    "total": 7.057983600000126,
                    "count": 5,
                    "self": 7.057983600000126
                },
                "TrainerController.advance": {
                    "total": 1314.4170516000336,
                    "count": 250048,
                    "self": 2.4724856000475484,
                    "children": {
                        "env_step": {
                            "total": 1225.0876588000144,
                            "count": 250048,
                            "self": 1100.2859882000184,
                            "children": {
                                "SubprocessEnvManager._take_step": {
                                    "total": 123.08616019997314,
                                    "count": 250048,
                                    "self": 6.93917579999264,
                                    "children": {
                                        "TorchPolicy.evaluate": {
                                            "total": 116.1469843999805,
                                            "count": 250048,
                                            "self": 32.07764329996982,
                                            "children": {
                                                "TorchPolicy.sample_actions": {
                                                    "total": 84.06934110001067,
                                                    "count": 250048,
                                                    "self": 84.06934110001067
                                                }
                                            }
                                        }
                                    }
                                },
                                "workers": {
                                    "total": 1.7155104000229713,
                                    "count": 250048,
                                    "self": 0.0,
                                    "children": {
                                        "worker_root": {
                                            "total": 1312.9234128000337,
                                            "count": 250048,
                                            "is_parallel": true,
                                            "self": 334.1613811999956,
                                            "children": {
                                                "steps_from_proto": {
                                                    "total": 0.0010202000001937606,
                                                    "count": 5,
                                                    "is_parallel": true,
                                                    "self": 0.0006351999999365532,
                                                    "children": {
                                                        "_process_rank_one_or_two_observation": {
                                                            "total": 0.0003850000002572074,
                                                            "count": 10,
                                                            "is_parallel": true,
                                                            "self": 0.0003850000002572074
                                                        }
                                                    }
                                                },
                                                "UnityEnvironment.step": {
                                                    "total": 978.7610114000379,
                                                    "count": 250048,
                                                    "is_parallel": true,
                                                    "self": 11.19559690005849,
                                                    "children": {
                                                        "UnityEnvironment._generate_step_input": {
                                                            "total": 10.415921799987736,
                                                            "count": 250048,
                                                            "is_parallel": true,
                                                            "self": 10.415921799987736
                                                        },
                                                        "communicator.exchange": {
                                                            "total": 919.1753503000081,
                                                            "count": 250048,
                                                            "is_parallel": true,
                                                            "self": 919.1753503000081
                                                        },
                                                        "steps_from_proto": {
                                                            "total": 37.97414239998362,
                                                            "count": 250048,
                                                            "is_parallel": true,
                                                            "self": 25.09440919993414,
                                                            "children": {
                                                                "_process_rank_one_or_two_observation": {
                                                                    "total": 12.879733200049479,
                                                                    "count": 500096,
                                                                    "is_parallel": true,
                                                                    "self": 12.879733200049479
                                                                }
                                                            }
                                                        }
                                                    }
                                                }
                                            }
                                        }
                                    }
                                }
                            }
                        },
                        "trainer_advance": {
                            "total": 86.85690719997166,
                            "count": 250048,
                            "self": 5.703224699987459,
                            "children": {
                                "process_trajectory": {
                                    "total": 18.015685099983877,
                                    "count": 250048,
                                    "self": 17.91118039998387,
                                    "children": {
                                        "RLTrainer._checkpoint": {
                                            "total": 0.10450470000000678,
                                            "count": 1,
                                            "self": 0.10450470000000678
                                        }
                                    }
                                },
                                "_update_policy": {
                                    "total": 63.137997400000316,
                                    "count": 48,
                                    "self": 41.938771499997536,
                                    "children": {
                                        "TorchPPOOptimizer.update": {
                                            "total": 21.19922590000278,
                                            "count": 1440,
                                            "self": 21.19922590000278
                                        }
                                    }
                                }
                            }
                        }
                    }
                },
                "trainer_threads": {
                    "total": 6.000000212225132e-07,
                    "count": 1,
                    "self": 6.000000212225132e-07
                },
                "TrainerController._save_models": {
                    "total": 0.036259200000131386,
                    "count": 1,
                    "self": 0.003763200000321376,
                    "children": {
                        "RLTrainer._checkpoint": {
                            "total": 0.03249599999981001,
                            "count": 1,
                            "self": 0.03249599999981001
                        }
                    }
                }
            }
        }
    }
}